tm1637/__init__.py
tm1637/tm1637.py
tm1637_rpi5_gpiod-2.0.0.dist-info/licenses/LICENSE
tm1637_rpi5_gpiod-2.0.0.dist-info/METADATA
tm1637_rpi5_gpiod-2.0.0.dist-info/WHEEL
tm1637_rpi5_gpiod-2.0.0.dist-info/top_level.txt
tm1637_rpi5_gpiod-2.0.0.dist-info/RECORD
