Metadata-Version: 2.4
Name: tm1637-rpi5-gpiod
Version: 2.0.0
Summary: TM1637 4-digit display driver for Raspberry Pi 5 using gpiod
Home-page: https://github.com/villeparamio/tm1637-rpi5-gpiod
Author: villeparamio
License: MIT
Classifier: Programming Language :: Python :: 3
Classifier: License :: OSI Approved :: MIT License
Classifier: Operating System :: POSIX :: Linux
Classifier: Intended Audience :: Developers
Classifier: Topic :: System :: Hardware :: Hardware Drivers
Requires-Python: >=3.7
License-File: LICENSE
Requires-Dist: gpiod
Dynamic: author
Dynamic: classifier
Dynamic: description
Dynamic: description-content-type
Dynamic: home-page
Dynamic: license
Dynamic: license-file
Dynamic: requires-dist
Dynamic: requires-python
Dynamic: summary
